Workbook

Sheet Assumptions
A1: SEO CHANNEL FORECAST — ASSUMPTIONS (edit yellow cells; everything else recalculates)
A3: Lever | B3: Value | C3: Unit | D3: Note
A4: Kit AOV (blended) | B4: 135 | C4: GBP | D4: Mix of Kit 1 £99 / Kit 2 £119 / Kit 3 £179 / Kit 3 Plus £239
A5: Supplement + retest uplift / customer | B5: 25 | C5: GBP | D5: ~20-30% attach; LTV £37.50 (3-mo) -> £77.32 (12-mo tenure)
A6: Effective revenue / kit customer | B6: =B4+B5 | D6: AOV + supplement/retest uplift (18-mo window)
A8: Blog -> kit conversion | B8: Rate | D8: Note
A9: Conservative | B9: 0.003 | D9: Mostly informational traffic; weak funnel
A10: Base | B10: 0.005 | D10: Semi-commercial 'X blood test' terms + CIO nurture
A11: Strong | B11: 0.01 | D11: High commercial-intent mix + tight CRO
A13: Downstream CQC/TRT cohort (post-18mo prize) | B13: Value | D13: Note
A14: TRT conversion of wellness cohort | B14: 0.12 | D14: Share of kit customers -> TRT after CQC
A15: TRT ARPU / month | B15: 200 | D15: Model: men pay £185-220/mo new-brand TRT
A16: Billed months (Year-1 of TRT) | B16: 12 | D16: First 12 months of the TRT subscription

Sheet Traffic_Ramp
A1: MONTHLY ORGANIC SESSIONS (edit any cell; back-loaded by design — SEO matures M12-18)
A3: Month | B3: Conservative | C3: Base | D3: Strong
A4: M1 | B4: 120 | C4: 200 | D4: 400
A5: M2 | B5: 280 | C5: 500 | D5: 1000
A6: M3 | B6: 480 | C6: 900 | D6: 1800
A7: M4 | B7: 720 | C7: 1500 | D7: 3000
A8: M5 | B8: 1050 | C8: 2500 | D8: 5000
A9: M6 | B9: 1500 | C9: 4000 | D9: 7000
A10: M7 | B10: 2100 | C10: 6000 | D10: 10000
A11: M8 | B11: 2900 | C11: 8500 | D11: 14000
A12: M9 | B12: 3900 | C12: 12000 | D12: 18000
A13: M10 | B13: 5200 | C13: 15000 | D13: 23000
A14: M11 | B14: 6500 | C14: 18000 | D14: 28000
A15: M12 | B15: 8000 | C15: 20000 | D15: 32000
... A21: M18 | B21: 18000 | C21: 40000 | D21: 70000
A22: 18-mo total | B22: =SUM(B4:B21) | C22: =SUM(C4:C21) | D22: =SUM(D4:D21)

Sheet Forecast
A1: 18-MONTH SEO REVENUE FORECAST (all formulas — driven by Assumptions + Traffic_Ramp)
B2: CONSERVATIVE | E2: BASE | H2: STRONG
A3: Month | B3: Sessions | C3: Customers | D3: Revenue | E3: Sessions | F3: Customers | G3: Revenue | H3: Sessions | I3: Customers | J3: Revenue
A4: M1 | B4: =Traffic_Ramp!B4 | C4: =Traffic_Ramp!B4*Assumptions!$B$9 | D4: =C4*Assumptions!$B$6 | E4: =Traffic_Ramp!C4 | F4: =Traffic_Ramp!C4*Assumptions!$B$10 | G4: =F4*Assumptions!$B$6 | H4: =Traffic_Ramp!D4 | I4: =Traffic_Ramp!D4*Assumptions!$B$11 | J4: =I4*Assumptions!$B$6
A5: M2 | B5: =Traffic_Ramp!B5 | C5: =Traffic_Ramp!B5*Assumptions!$B$9 | D5: =C5*Assumptions!$B$6 | E5: =Traffic_Ramp!C5 | F5: =Traffic_Ramp!C5*Assumptions!$B$10 | G5: =F5*Assumptions!$B$6 | H5: =Traffic_Ramp!D5 | I5: =Traffic_Ramp!D5*Assumptions!$B$11 | J5: =I5*Assumptions!$B$6
A6: M3 | B6: =Traffic_Ramp!B6 | C6: =Traffic_Ramp!B6*Assumptions!$B$9 | D6: =C6*Assumptions!$B$6 | E6: =Traffic_Ramp!C6 | F6: =Traffic_Ramp!C6*Assumptions!$B$10 | G6: =F6*Assumptions!$B$6 | H6: =Traffic_Ramp!D6 | I6: =Traffic_Ramp!D6*Assumptions!$B$11 | J6: =I6*Assumptions!$B$6
A7: M4 | B7: =Traffic_Ramp!B7 | C7: =Traffic_Ramp!B7*Assumptions!$B$9 | D7: =C7*Assumptions!$B$6 | E7: =Traffic_Ramp!C7 | F7: =Traffic_Ramp!C7*Assumptions!$B$10 | G7: =F7*Assumptions!$B$6 | H7: =Traffic_Ramp!D7 | I7: =Traffic_Ramp!D7*Assumptions!$B$11 | J7: =I7*Assumptions!$B$6
A8: M5 | B8: =Traffic_Ramp!B8 | C8: =Traffic_Ramp!B8*Assumptions!$B$9 | D8: =C8*Assumptions!$B$6 | E8: =Traffic_Ramp!C8 | F8: =Traffic_Ramp!C8*Assumptions!$B$10 | G8: =F8*Assumptions!$B$6 | H8: =Traffic_Ramp!D8 | I8: =Traffic_Ramp!D8*Assumptions!$B$11 | J8: =I8*Assumptions!$B$6
A9: M6 | B9: =Traffic_Ramp!B9 | C9: =Traffic_Ramp!B9*Assumptions!$B$9 | D9: =C9*Assumptions!$B$6 | E9: =Traffic_Ramp!C9 | F9: =Traffic_Ramp!C9*Assumptions!$B$10 | G9: =F9*Assumptions!$B$6 | H9: =Traffic_Ramp!D9 | I9: =Traffic_Ramp!D9*Assumptions!$B$11 | J9: =I9*Assumptions!$B$6
A10: M7 | B10: =Traffic_Ramp!B10 | C10: =Traffic_Ramp!B10*Assumptions!$B$9 | D10: =C10*Assumptions!$B$6 | E10: =Traffic_Ramp!C10 | F10: =Traffic_Ramp!C10*Assumptions!$B$10 | G10: =F10*Assumptions!$B$6 | H10: =Traffic_Ramp!D10 | I10: =Traffic_Ramp!D10*Assumptions!$B$11 | J10: =I10*Assumptions!$B$6
A11: M8 | B11: =Traffic_Ramp!B11 | C11: =Traffic_Ramp!B11*Assumptions!$B$9 | D11: =C11*Assumptions!$B$6 | E11: =Traffic_Ramp!C11 | F11: =Traffic_Ramp!C11*Assumptions!$B$10 | G11: =F11*Assumptions!$B$6 | H11: =Traffic_Ramp!D11 | I11: =Traffic_Ramp!D11*Assumptions!$B$11 | J11: =I11*Assumptions!$B$6
A12: M9 | B12: =Traffic_Ramp!B12 | C12: =Traffic_Ramp!B12*Assumptions!$B$9 | D12: =C12*Assumptions!$B$6 | E12: =Traffic_Ramp!C12 | F12: =Traffic_Ramp!C12*Assumptions!$B$10 | G12: =F12*Assumptions!$B$6 | H12: =Traffic_Ramp!D12 | I12: =Traffic_Ramp!D12*Assumptions!$B$11 | J12: =I12*Assumptions!$B$6
A13: M10 | B13: =Traffic_Ramp!B13 | C13: =Traffic_Ramp!B13*Assumptions!$B$9 | D13: =C13*Assumptions!$B$6 | E13: =Traffic_Ramp!C13 | F13: =Traffic_Ramp!C13*Assumptions!$B$10 | G13: =F13*Assumptions!$B$6 | H13: =Traffic_Ramp!D13 | I13: =Traffic_Ramp!D13*Assumptions!$B$11 | J13: =I13*Assumptions!$B$6
A14: M11 | B14: =Traffic_Ramp!B14 | C14: =Traffic_Ramp!B14*Assumptions!$B$9 | D14: =C14*Assumptions!$B$6 | E14: =Traffic_Ramp!C14 | F14: =Traffic_Ramp!C14*Assumptions!$B$10 | G14: =F14*Assumptions!$B$6 | H14: =Traffic_Ramp!D14 | I14: =Traffic_Ramp!D14*Assumptions!$B$11 | J14: =I14*Assumptions!$B$6
A15: M12 | B15: =Traffic_Ramp!B15 | C15: =Traffic_Ramp!B15*Assumptions!$B$9 | D15: =C15*Assumptions!$B$6 | E15: =Traffic_Ramp!C15 | F15: =Traffic_Ramp!C15*Assumptions!$B$10 | G15: =F15*Assumptions!$B$6 | H15: =Traffic_Ramp!D15 | I15: =Traffic_Ramp!D15*Assumptions!$B$11 | J15: =I15*Assumptions!$B$6
... A21: M18 | B21: =Traffic_Ramp!B21 | C21: =Traffic_Ramp!B21*Assumptions!$B$9 | D21: =C21*Assumptions!$B$6 | E21: =Traffic_Ramp!C21 | F21: =Traffic_Ramp!C21*Assumptions!$B$10 | G21: =F21*Assumptions!$B$6 | H21: =Traffic_Ramp!D21 | I21: =Traffic_Ramp!D21*Assumptions!$B$11 | J21: =I21*Assumptions!$B$6
A22: 18-MO TOTAL | B22: =SUM(B4:B21) | C22: =SUM(C4:C21) | D22: =SUM(D4:D21) | E22: =SUM(E4:E21) | F22: =SUM(F4:F21) | G22: =SUM(G4:G21) | H22: =SUM(H4:H21) | I22: =SUM(I4:I21) | J22: =SUM(J4:J21)
A23: M18 run-rate (orders/wk) | D23: =C21/4.33 | G23: =F21/4.33 | J23: =I21/4.33

Sheet Downstream
A1: WHY THE 18-MONTH NUMBER UNDERSTATES IT (the content is feeding these)
A3: 1. COMPOUNDING TRAFFIC ASSET
A4: M18 sessions are the launch pad for Year 2-3; same content typically 2-3x's with no extra spend.
A5: The 18-mo revenue is the bottom of the curve, not the plateau.
A7: 2. PRE-QUALIFIED CQC / TRT COHORT (quantified below)
A8: Every kit customer is a warm lead for TRT at ~80% margin post-CQC. Most of this lands JUST past 18 months.
A10: 3. AI-CITATION UPSIDE (Pillar F) — unmodellable; if the original-data + Ewa E-E-A-T play lands it's a step-change.
A12: Downstream TRT value from the 18-mo cohort | B12: Conservative | C12: Base | D12: Strong
A13: 18-mo kit customers (from Forecast) | B13: =Forecast!C22 | C13: =Forecast!F22 | D13: =Forecast!I22
A14: -> annual TRT revenue if cohort converts | B14: =B13*Assumptions!$B$14*Assumptions!$B$15*Assumptions!$B$16 | C14: =C13*Assumptions!$B$14*Assumptions!$B$15*Assumptions!$B$16 | D14: =D13*Assumptions!$B$14*Assumptions!$B$15*Assumptions!$B$16
A16: Illustrative annual recurring TRT revenue the wellness cohort seeds (lands post-CQC, mostly beyond month 18).
A17: Compare to the 18-mo direct kit line on Forecast — the recurring clinical line is the larger prize.
