Workbook

Sheet Assumptions
A1: ANDRO PRIME — PHASE 0 FINANCIAL MODEL V7.2
A2: Organic-First | Zero Paid Media | Premium Positioning | April 2026
A4: KIT UNIT ECONOMICS (Vitall Finger-Prick)
B5: COGS (Vitall) | C5: Retail Price | D5: Gross Margin £ | E5: Gross Margin %
A6: Kit 1 — Hormone Check | B6: 58.5 | C6: 89 | D6: =C6-B6 -> 30.5 | E6: =D6/C6 -> 0.34269663
A7: Kit 2 — Energy & Metabolism | B7: 63 | C7: 99 | D7: =C7-B7 -> 36 | E7: =D7/C7 -> 0.36363636
A8: Kit 3 — Combo Test | B8: 98 | C8: 149 | D8: =C8-B8 -> 51 | E8: =D8/C8 -> 0.34228188
A10: SUPPLEMENT UNIT ECONOMICS (Market Research Est.)
B11: COGS (Est.) | C11: Sub Price /mo | D11: Gross Margin £ | E11: Gross Margin %
A12: Daily Stack | B12: 15 | C12: 34.95 | D12: =C12-B12 -> 19.95 | E12: =D12/C12 -> 0.57081545
A13: Joint & Recovery Collagen | B13: 13 | C13: 29.95 | D13: =C13-B13 -> 16.95 | E13: =D13/C13 -> 0.56594324
A14: Complete Stack (Bundle) | B14: =B12+B13 -> 28 | C14: 54.95 | D14: =C14-B14 -> 26.95 | E14: =D14/C14 -> 0.49044586
A16: OPERATING ASSUMPTIONS
A17: Assumption | B17: Value | C17: Notes
A18: Payment processing (Stripe %) | B18: 0.025 | C18: Applied to all revenue
A19: Affiliate commission rate | B19: 0.125 | C19: 12.5% (reduced from 20%)
A20: Affiliate mix (% of kit sales) | B20: 0.2 | C20: Conservative — organic-led model
A21: Kit-to-supplement conversion | B21: 0.12 | C21: 12% of Kit 2/3 buyers
A22: Supplement monthly churn | B22: 0.03 | C22: 3% monthly
A23: Founding member deposit £ | B23: 75 | C23: £75 per deposit
A24: Low-T rate (Kit 1 + Kit 3) | B24: 0.35 | C24: 35% of testosterone-tested men
A25: Deposit conversion (of low-T) | B25: 0.5 | C25: 50% of low-T results deposit
A26: Paid media budget /month | B26: 0 | C26: Zero — organic/affiliate only
A28: MONTHLY FIXED OVERHEAD
A29: Cost Item | B29: Monthly £ | C29: Notes
A30: Website hosting | B30: 25 | C30: Vercel free tier → ~£25
A31: Domain & SSL | B31: 5 | C31: ~£60/year
A32: Email/CRM (Customer.io) | B32: 150 | C32: Essentials plan, small list
A33: Design tools (Canva Pro) | B33: 13 | C33: £155/year
A34: Bookkeeping / accountant | B34: 200 | C34: Monthly retainer
A35: Product liability insurance | B35: 75 | C35: ~£900/year
A36: Customer support tools | B36: 0 | C36: Free tier initially (Crisp/Tawk)
A37: Phone/comms | B37: 30 | C37: Business mobile
A38: Misc/contingency | B38: 50 | C38: Returns, replacements, postage
A39: FSA compliance review | B39: 42 | C39: ~£500/year periodic
A40: ICO data protection fee | B40: 3 | C40: £35/year Tier 1
A42: TOTAL MONTHLY OVERHEAD | B42: =SUM(B30:B40) -> 593
A44: LAUNCH CAPITAL (Vitall white-label = £0)
A45: Item | B45: Amount | C45: Notes
A46: Website build (tooling costs) | B46: 0 | C46: £0 — Vitall white-label, all costs in per-kit COGS
A47: Packaging design / branding | B47: 0 | C47: £0 — Vitall handles packaging
A48: Lab partner setup (Vitall) | B48: 0 | C48: £0 — No setup fee
A49: Contingency | B49: 0 | C49: £0 — No contingency needed
A50: TOTAL LAUNCH CAPITAL (Kits Only) | B50: =SUM(B46:B49) -> 0
A52: SUPPLEMENT CAPITAL (Self-Funded from Kit Revenue)
A53: Item | B53: Amount | C53: Notes
A54: Daily Stack MOQ (500-1000 units) | B54: 4000 | C54: Funded from accumulated kit profits — order when cash available
A55: Collagen MOQ (500 units) | B55: 1500 | C55: Funded from accumulated kit profits
A56: Label design + compliance review | B56: 2000 | C56: FSA-compliant labels, Ewa review
A57: Stability testing (2 SKUs) | B57: 1500 | C57: Non-negotiable for FSA compliance
A58: TOTAL SUPPLEMENT CAPITAL | B58: =SUM(B54:B57) -> 9000
A60: PHASED OPTION: Daily Stack Only First
A61: Daily Stack MOQ (500 units) | B61: 4000 | C61: Reachable by ~Month 4-5 from kit profits
A62: Label + compliance (1 SKU) | B62: 1200 | C62: This is your minimum monthly kit target
A63: Stability testing (1 SKU) | B63: 750
A64: TOTAL PHASED SUPPLEMENT CAPITAL | B64: =SUM(B61:B63) -> 5950
A66: MONTHLY BREAKEVEN ANALYSIS
A67: Blended kit margin (after COGS, Stripe, affiliate) | B67: =(1-B20)*(((C6-B6)-C6*B18)+(C7-B7-C7*B18)+(C8-B8-C8*B18))/3 + B20*(((C6-B6)-C6*B18-C6*B19)+((C7-B7)-C7*B18-C7*B19)+((C8-B8)-C8*B18-C8*B19))/3 -> 33.55 | C67: Average across all 3 kits, weighted by affiliate mix
A68: Kits needed per month to cover overhead | B68: =ROUNDUP(B42/B67,0) -> 18 | C68: This is your minimum monthly kit target
A69: That's approximately per week | B69: =ROUNDUP(B68/4.33,0) -> 5
A71: Months to accumulate full supplement capital (£9k) | B71: =ROUNDUP(B58/((B67*25)-B42),0) -> 37 | C71: At ~25 kits/month average
A72: Months to accumulate phased capital (Daily Stack only) | B72: =ROUNDUP(B64/((B67*25)-B42),0) -> 25 | C72: At ~25 kits/month average

Sheet 6-Month P&L
A1: PHASE 0 — 6-MONTH P&L (V7.2)
A2: Organic-First | Zero Paid Media | Cash-Positive Target Month 1
B4: Month 1 | C4: Month 2 | D4: Month 3 | E4: Month 4 | F4: Month 5 | G4: Month 6 | H4: 6-Mo Total
A5: KIT SALES VOLUME
A6: Kit 1 — Hormone Check | B6: 5 | C6: 8 | D6: 10 | E6: 12 | F6: 15 | G6: 18 | H6: =SUM(B6:G6) -> 68
A7: Kit 2 — Energy & Metabolism | B7: 12 | C7: 16 | D7: 22 | E7: 28 | F7: 32 | G7: 38 | H7: =SUM(B7:G7) -> 148
A8: Kit 3 — Combo Test | B8: 0 | C8: 3 | D8: 5 | E8: 8 | F8: 10 | G8: 12 | H8: =SUM(B8:G8) -> 38
A9: Total Kits Sold | B9: =B6+B7+B8 -> 17 | C9: =C6+C7+C8 -> 27 | D9: =D6+D7+D8 -> 37 | E9: =E6+E7+E8 -> 48 | F9: =F6+F7+F8 -> 57 | G9: =G6+G7+G8 -> 68 | H9: =H6+H7+H8 -> 254
A10: Cumulative Kits | B10: =B9 -> 17 | C10: =B10+C9 -> 44 | D10: =C10+D9 -> 81 | E10: =D10+E9 -> 129 | F10: =E10+F9 -> 186 | G10: =F10+G9 -> 254 | H10: =G10 -> 254
A12: KIT REVENUE
A13: Kit 1 — Revenue Hormone Check | B13: =B6*Assumptions!C6 -> 445 | C13: =C6*Assumptions!C6 -> 712 | D13: =D6*Assumptions!C6 -> 890 | E13: =E6*Assumptions!C6 -> 1068 | F13: =F6*Assumptions!C6 -> 1335 | G13: =G6*Assumptions!C6 -> 1602 | H13: =SUM(B13:G13) -> 6052
A14: Kit 2 — Revenue Energy & Metabolism | B14: =B7*Assumptions!C7 -> 1188 | C14: =C7*Assumptions!C7 -> 1584 | D14: =D7*Assumptions!C7 -> 2178 | E14: =E7*Assumptions!C7 -> 2772 | F14: =F7*Assumptions!C7 -> 3168 | G14: =G7*Assumptions!C7 -> 3762 | H14: =SUM(B14:G14) -> 14652
A15: Kit 3 — Revenue Combo Test | B15: =B8*Assumptions!C8 -> 0 | C15: =C8*Assumptions!C8 -> 447 | D15: =D8*Assumptions!C8 -> 745 | E15: =E8*Assumptions!C8 -> 1192 | F15: =F8*Assumptions!C8 -> 1490 | G15: =G8*Assumptions!C8 -> 1788 | H15: =SUM(B15:G15) -> 5662
A16: Total Kit Revenue | B16: =B13+B14+B15 -> 1633 | C16: =C13+C14+C15 -> 2743 | D16: =D13+D14+D15 -> 3813 | E16: =E13+E14+E15 -> 5032 | F16: =F13+F14+F15 -> 5993 | G16: =G13+G14+G15 -> 7152 | H16: =H13+H14+H15 -> 26366
A18: KIT COGS
A19: Kit 1 — COGS Hormone Check | B19: =B6*Assumptions!B6 -> 292.5 | C19: =C6*Assumptions!B6 -> 468 | D19: =D6*Assumptions!B6 -> 585 | E19: =E6*Assumptions!B6 -> 702 | F19: =F6*Assumptions!B6 -> 877.5 | G19: =G6*Assumptions!B6 -> 1053 | H19: =SUM(B19:G19) -> 3978
A20: Kit 2 — COGS Energy & Metabolism | B20: =B7*Assumptions!B7 -> 756 | C20: =C7*Assumptions!B7 -> 1008 | D20: =D7*Assumptions!B7 -> 1386 | E20: =E7*Assumptions!B7 -> 1764 | F20: =F7*Assumptions!B7 -> 2016 | G20: =G7*Assumptions!B7 -> 2394 | H20: =SUM(B20:G20) -> 9324
A21: Kit 3 — COGS Combo Test | B21: =B8*Assumptions!B8 -> 0 | C21: =C8*Assumptions!B8 -> 294 | D21: =D8*Assumptions!B8 -> 490 | E21: =E8*Assumptions!B8 -> 784 | F21: =F8*Assumptions!B8 -> 980 | G21: =G8*Assumptions!B8 -> 1176 | H21: =SUM(B21:G21) -> 3724
A22: Total Kit COGS | B22: =B19+B20+B21 -> 1048.5 | C22: =C19+C20+C21 -> 1770 | D22: =D19+D20+D21 -> 2461 | E22: =E19+E20+E21 -> 3250 | F22: =F19+F20+F21 -> 3873.5 | G22: =G19+G20+G21 -> 4623 | H22: =H19+H20+H21 -> 17026
A24: Kit Gross Profit | B24: =B16-B22 -> 584.5 | C24: =C16-C22 -> 973 | D24: =D16-D22 -> 1352 | E24: =E16-E22 -> 1782 | F24: =F16-F22 -> 2119.5 | G24: =G16-G22 -> 2529 | H24: =H16-H22 -> 9340
A25: Kit Gross Margin % | B25: =IF(B16=0,0,B24/B16) -> 0.35793019 | C25: =IF(C16=0,0,C24/C16) -> 0.35472111 | D25: =IF(D16=0,0,D24/D16) -> 0.35457645 | E25: =IF(E16=0,0,E24/E16) -> 0.35413355 | F25: =IF(F16=0,0,F24/F16) -> 0.35366261 | G25: =IF(G16=0,0,G24/G16) -> 0.35360738 | H25: =IF(H16=0,0,H24/H16) -> 0.3542441
A27: SUPPLEMENT SUBSCRIBERS
A28: New subs (12% of Kit 2+3 buyers) | B28: =ROUND((B7+B8)*Assumptions!B21,0) -> 1 | C28: =ROUND((C7+C8)*Assumptions!B21,0) -> 2 | D28: =ROUND((D7+D8)*Assumptions!B21,0) -> 3 | E28: =ROUND((E7+E8)*Assumptions!B21,0) -> 4 | F28: =ROUND((F7+F8)*Assumptions!B21,0) -> 5 | G28: =ROUND((G7+G8)*Assumptions!B21,0) -> 6 | H28: =SUM(B28:G28) -> 21
A29: Churned subs | B29: 0 | C29: =ROUND(B30*Assumptions!B22,0) -> 0 | D29: =ROUND(C30*Assumptions!B22,0) -> 0 | E29: =ROUND(D30*Assumptions!B22,0) -> 0 | F29: =ROUND(E30*Assumptions!B22,0) -> 0 | G29: =ROUND(F30*Assumptions!B22,0) -> 0 | H29: =SUM(B29:G29) -> 0
A30: Active Subscribers (EOM) | B30: =B28-B29 -> 1 | C30: =B30+C28-C29 -> 3 | D30: =C30+D28-D29 -> 6 | E30: =D30+E28-E29 -> 10 | F30: =E30+F28-F29 -> 15 | G30: =F30+G28-G29 -> 21 | H30: =G30 -> 21
A32: SUPPLEMENT FINANCIALS
A33: Supplement Revenue | B33: =B30*Assumptions!C12 -> 34.95 | C33: =C30*Assumptions!C12 -> 104.85 | D33: =D30*Assumptions!C12 -> 209.7 | E33: =E30*Assumptions!C12 -> 349.5 | F33: =F30*Assumptions!C12 -> 524.25 | G33: =G30*Assumptions!C12 -> 733.95 | H33: =SUM(B33:G33) -> 1957.2
A34: Supplement COGS | B34: =B30*Assumptions!B12 -> 15 | C34: =C30*Assumptions!B12 -> 45 | D34: =D30*Assumptions!B12 -> 90 | E34: =E30*Assumptions!B12 -> 150 | F34: =F30*Assumptions!B12 -> 225 | G34: =G30*Assumptions!B12 -> 315 | H34: =SUM(B34:G34) -> 840
A35: Supplement Gross Profit | B35: =B33-B34 -> 19.95 | C35: =C33-C34 -> 59.85 | D35: =D33-D34 -> 119.7 | E35: =E33-E34 -> 199.5 | F35: =F33-F34 -> 299.25 | G35: =G33-G34 -> 418.95 | H35: =H33-H34 -> 1117.2
A37: FOUNDING MEMBER DEPOSITS
A38: T-kits sold (Kit 1 + Kit 3) | B38: =B6+B8 -> 5 | C38: =C6+C8 -> 11 | D38: =D6+D8 -> 15 | E38: =E6+E8 -> 20 | F38: =F6+F8 -> 25 | G38: =G6+G8 -> 30 | H38: =SUM(B38:G38) -> 106
A39: Low-T results (35%) | B39: =ROUND(B38*Assumptions!B24,0) -> 2 | C39: =ROUND(C38*Assumptions!B24,0) -> 4 | D39: =ROUND(D38*Assumptions!B24,0) -> 5 | E39: =ROUND(E38*Assumptions!B24,0) -> 7 | F39: =ROUND(F38*Assumptions!B24,0) -> 9 | G39: =ROUND(G38*Assumptions!B24,0) -> 11 | H39: =SUM(B39:G39) -> 38
A40: Deposits secured (50%) | B40: =ROUND(B39*Assumptions!B25,0) -> 1 | C40: =ROUND(C39*Assumptions!B25,0) -> 2 | D40: =ROUND(D39*Assumptions!B25,0) -> 3 | E40: =ROUND(E39*Assumptions!B25,0) -> 4 | F40: =ROUND(F39*Assumptions!B25,0) -> 5 | G40: =ROUND(G39*Assumptions!B25,0) -> 6 | H40: =SUM(B40:G40) -> 21
A41: Deposit Revenue | B41: =B40*Assumptions!B23 -> 75 | C41: =C40*Assumptions!B23 -> 150 | D41: =D40*Assumptions!B23 -> 225 | E41: =E40*Assumptions!B23 -> 300 | F41: =F40*Assumptions!B23 -> 375 | G41: =G40*Assumptions!B23 -> 450 | H41: =SUM(B41:G41) -> 1575
A43: REVENUE SUMMARY
A44: Kit Revenue | B44: =B16 -> 1633 | C44: =C16 -> 2743 | D44: =D16 -> 3813 | E44: =E16 -> 5032 | F44: =F16 -> 5993 | G44: =G16 -> 7152 | H44: =H16 -> 26366
A45: Supplement Revenue | B45: =B33 -> 34.95 | C45: =C33 -> 104.85 | D45: =D33 -> 209.7 | E45: =E33 -> 349.5 | F45: =F33 -> 524.25 | G45: =G33 -> 733.95 | H45: =H33 -> 1957.2
A46: Deposit Revenue | B46: =B41 -> 75 | C46: =C41 -> 150 | D46: =D41 -> 225 | E46: =E41 -> 300 | F46: =F41 -> 375 | G46: =G41 -> 450 | H46: =H41 -> 1575
A47: TOTAL REVENUE | B47: =B44+B45+B46 -> 1742.95 | C47: =C44+C45+C46 -> 2997.85 | D47: =D44+D45+D46 -> 4247.7 | E47: =E44+E45+E46 -> 5681.5 | F47: =F44+F45+F46 -> 6892.25 | G47: =G44+G45+G46 -> 8335.95 | H47: =H44+H45+H46 -> 29898.2
A49: TOTAL COGS
A50: Kit COGS | B50: =B22 -> 1048.5 | C50: =C22 -> 1770 | D50: =D22 -> 2461 | E50: =E22 -> 3250 | F50: =F22 -> 3873.5 | G50: =G22 -> 4623 | H50: =H22 -> 17026
A51: Supplement COGS | B51: =B34 -> 15 | C51: =C34 -> 45 | D51: =D34 -> 90 | E51: =E34 -> 150 | F51: =F34 -> 225 | G51: =G34 -> 315 | H51: =H34 -> 840
A52: TOTAL COGS | B52: =B50+B51 -> 1063.5 | C52: =C50+C51 -> 1815 | D52: =D50+D51 -> 2551 | E52: =E50+E51 -> 3400 | F52: =F50+F51 -> 4098.5 | G52: =G50+G51 -> 4938 | H52: =H50+H51 -> 17866
A54: GROSS PROFIT | B54: =B47-B52 -> 679.45 | C54: =C47-C52 -> 1182.85 | D54: =D47-D52 -> 1696.7 | E54: =E47-E52 -> 2281.5 | F54: =F47-F52 -> 2793.75 | G54: =G47-G52 -> 3397.95 | H54: =H47-H52 -> 12032.2
A55: Gross Margin % | B55: =IF(B47=0,0,B54/B47) -> 0.38982759 | C55: =IF(C47=0,0,C54/C47) -> 0.39456611 | D55: =IF(D47=0,0,D54/D47) -> 0.3994397 | E55: =IF(E47=0,0,E54/E47) -> 0.40156649 | F55: =IF(F47=0,0,F54/F47) -> 0.40534658 | G55: =IF(G47=0,0,G54/G47) -> 0.40762601 | H55: =IF(H47=0,0,H54/H47) -> 0.40243894
A57: OPERATING EXPENSES
A58: Fixed Overhead | B58: =Assumptions!B42 -> 593 | C58: =Assumptions!B42 -> 593 | D58: =Assumptions!B42 -> 593 | E58: =Assumptions!B42 -> 593 | F58: =Assumptions!B42 -> 593 | G58: =Assumptions!B42 -> 593 | H58: =SUM(B58:G58) -> 3558
A59: Paid Media | B59: =Assumptions!B26 -> 0 | C59: =Assumptions!B26 -> 0 | D59: =Assumptions!B26 -> 0 | E59: =Assumptions!B26 -> 0 | F59: =Assumptions!B26 -> 0 | G59: =Assumptions!B26 -> 0 | H59: =SUM(B59:G59) -> 0
A60: Payment Processing (Stripe) | B60: =B47*Assumptions!B18 -> 43.57375 | C60: =C47*Assumptions!B18 -> 74.94625 | D60: =D47*Assumptions!B18 -> 106.1925 | E60: =E47*Assumptions!B18 -> 142.0375 | F60: =F47*Assumptions!B18 -> 172.30625 | G60: =G47*Assumptions!B18 -> 208.39875 | H60: =SUM(B60:G60) -> 747.455
A61: Affiliate Commissions | B61: =B16*Assumptions!B20*Assumptions!B19 -> 40.825 | C61: =C16*Assumptions!B20*Assumptions!B19 -> 68.575 | D61: =D16*Assumptions!B20*Assumptions!B19 -> 95.325 | E61: =E16*Assumptions!B20*Assumptions!B19 -> 125.8 | F61: =F16*Assumptions!B20*Assumptions!B19 -> 149.825 | G61: =G16*Assumptions!B20*Assumptions!B19 -> 178.8 | H61: =SUM(B61:G61) -> 659.15
A62: TOTAL OPEX | B62: =SUM(B58:B61) -> 677.39875 | C62: =SUM(C58:C61) -> 736.52125 | D62: =SUM(D58:D61) -> 794.5175 | E62: =SUM(E58:E61) -> 860.8375 | F62: =SUM(F58:F61) -> 915.13125 | G62: =SUM(G58:G61) -> 980.19875 | H62: =SUM(H58:H61) -> 4964.605
A64: NET MONTHLY CONTRIBUTION | B64: =B54-B62 -> 2.05125 | C64: =C54-C62 -> 446.32875 | D64: =D54-D62 -> 902.1825 | E64: =E54-E62 -> 1420.6625 | F64: =F54-F62 -> 1878.6188 | G64: =G54-G62 -> 2417.7512 | H64: =H54-H62 -> 7067.595
A65: Net Margin % | B65: =IF(B47=0,0,B64/B47) -> 0.001176884 | C65: =IF(C47=0,0,C64/C47) -> 0.14888295 | D65: =IF(D47=0,0,D64/D47) -> 0.21239318 | E65: =IF(E47=0,0,E64/E47) -> 0.2500506 | F65: =IF(F47=0,0,F64/F47) -> 0.27256973 | G65: =IF(G47=0,0,G64/G47) -> 0.29003908 | H65: =IF(H47=0,0,H64/H47) -> 0.23638865
A67: CASH POSITION
A68: Launch Capital (£0 — Vitall white-label) | B68: 0
A69: Supplement Capital (phased — when funded) | C69: 0
A70: Cumulative Cash Position | B70: =B68+B64 -> 2.05125 | C70: =B70+C64+C69 -> 448.38 | D70: =C70+D64 -> 1350.5625 | E70: =D70+E64 -> 2771.225 | F70: =E70+F64 -> 4649.8438 | G70: =F70+G64 -> 7067.595 | H70: =G70 -> 7067.595
A72: KEY METRICS
A73: Blended Revenue per Kit | B73: =IF(B9=0,0,B16/B9) -> 96.058824 | C73: =IF(C9=0,0,C16/C9) -> 101.59259 | D73: =IF(D9=0,0,D16/D9) -> 103.05405 | E73: =IF(E9=0,0,E16/E9) -> 104.83333 | F73: =IF(F9=0,0,F16/F9) -> 105.14035 | G73: =IF(G9=0,0,G16/G9) -> 105.17647 | H73: =IF(H9=0,0,H16/H9) -> 103.80315
A74: Supplement MRR (EOM) | B74: =B30*Assumptions!C12 -> 34.95 | C74: =C30*Assumptions!C12 -> 104.85 | D74: =D30*Assumptions!C12 -> 209.7 | E74: =E30*Assumptions!C12 -> 349.5 | F74: =F30*Assumptions!C12 -> 524.25 | G74: =G30*Assumptions!C12 -> 733.95 | H74: =G74 -> 733.95
A75: Founding Member Deposits (cumulative) | B75: =B40 -> 1 | C75: =B75+C40 -> 3 | D75: =C75+D40 -> 6 | E75: =D75+E40 -> 10 | F75: =E75+F40 -> 15 | G75: =F75+G40 -> 21 | H75: =G75 -> 21
A76: Kit Revenue as % of Total | B76: =IF(B47=0,0,B16/B47) -> 0.9369173 | C76: =IF(C47=0,0,C16/C47) -> 0.91498908 | D76: =IF(D47=0,0,D16/D47) -> 0.89766226 | E76: =IF(E47=0,0,E16/E47) -> 0.8856816 | F76: =IF(F47=0,0,F16/F47) -> 0.86952737 | G76: =IF(G47=0,0,G16/G47) -> 0.8579706 | H76: =IF(H47=0,0,H16/H47) -> 0.88185911
