Workbook

Sheet Model Overview
A1: ANDRO PRIME — PHASE 0 FINANCIAL MODEL
A2: Premium Positioning | Organic-First | Zero External Funding
A3: Version 1.0 — April 2026
A5: MODEL IDENTITY
A6: Model name | B6: Phase 0 Financial Model v1.0
A7: Scope | B7: Non-regulated wellness tier only (kits + supplements)
A8: Excludes | B8: V5.0 TRT/clinical model — separate business
A9: Lab partner | B9: Vitall — finger-prick collection, white-label drop-ship
A10: Launch capital required | B10: £0 (all costs in per-kit COGS)
A11: Paid media budget | B11: £0 (organic + affiliate only)
A12: Affiliate model | B12: Flat £15/referral OR 15% commission (switchable)
A13: Planning stance | B13: Conservative — judge business against these numbers
A15: KEY OUTPUTS (from model)
A16: Monthly breakeven | B16: See Assumptions tab
A17: Month 1 net contribution | B17: See 6-Month P&L tab
A18: 6-month cumulative cash | B18: See 6-Month P&L tab
A19: Supplement capital timing | B19: Self-funded from kit profits

Sheet Assumptions
A1: ASSUMPTIONS & UNIT ECONOMICS
A2: All yellow cells are editable inputs — model recalculates automatically
A4: KIT UNIT ECONOMICS
B5: COGS (Vitall) | C5: Retail Price | D5: Gross Margin £ | E5: Gross Margin %
A6: Kit 1 — Hormone Check | B6: 58.5 | C6: 99 | D6: =C6-B6 -> 40.5 | E6: =D6/C6 -> 0.40909091
A7: Kit 2 — Energy & Metabolism | B7: 63 | C7: 119 | D7: =C7-B7 -> 56 | E7: =D7/C7 -> 0.47058824
A8: Kit 3 — Combo Test | B8: 98 | C8: 179 | D8: =C8-B8 -> 81 | E8: =D8/C8 -> 0.45251397
A10: KIT PANELS (Vitall Finger-Prick)
A11: Kit | B11: Biomarkers
A12: Kit 1 | B12: Free Testosterone, SHBG, Total Testosterone
A13: Kit 2 | B13: Vitamin D, Vitamin B12, Ferritin (Iron), hs-CRP (Inflammation)
A14: Kit 3 | B14: All Kit 1 + Kit 2 markers (6 total)
A16: SUPPLEMENT UNIT ECONOMICS (Est. — Pending Quotes)
B17: COGS (Est.) | C17: Sub Price /mo | D17: Gross Margin £ | E17: Gross Margin %
A18: Daily Stack | B18: 15 | C18: 34.95 | D18: =C18-B18 -> 19.95 | E18: =D18/C18 -> 0.57081545
A19: Joint & Recovery Collagen | B19: 13 | C19: 29.95 | D19: =C19-B19 -> 16.95 | E19: =D19/C19 -> 0.56594324
A20: Complete Stack (Bundle) | B20: =B18+B19 -> 28 | C20: 54.95 | D20: =C20-B20 -> 26.95 | E20: =D20/C20 -> 0.49044586
A22: OPERATING ASSUMPTIONS
A23: Assumption | B23: Value | C23: Notes
A24: Payment processing (Stripe) | B24: 0.025 | C24: 2.5% on all revenue
A25: Affiliate fee per referral (flat) | B25: 15 | C25: £15 flat per referred kit sale
A26: Affiliate mix (% of kit sales) | B26: 0.2 | C26: 20% of kits via affiliates
A27: Kit-to-supplement conversion | B27: 0.12 | C27: 12% of Kit 2/3 buyers subscribe
A28: Supplement monthly churn | B28: 0.03 | C28: 3% monthly
A29: Founding member deposit | B29: 75 | C29: £75 per deposit
A30: Low-T rate (Kit 1 + Kit 3 buyers) | B30: 0.35 | C30: 35% show T < 12 nmol/L
A31: Deposit conversion (of low-T) | B31: 0.5 | C31: 50% of low-T results deposit
A33: MONTHLY OVERHEAD (Lean Launch)
A34: Cost Item | B34: Monthly £ | C34: Notes
A35: CRM / Email (free tier) | B35: 0 | C35: Brevo/Mailchimp free until 500 contacts
A36: Website hosting | B36: 0 | C36: Vercel free tier
A37: Domain + SSL | B37: 5 | C37: ~£60/year
A38: Phone / comms | B38: 30 | C38: Business mobile
A39: Bookkeeping (self-managed initially) | B39: 0 | C39: Keith manages; accountant added at £200/mo when volume justifies
A40: Design tools (Canva free) | B40: 0 | C40: Free tier initially
A41: Insurance (deferred) | B41: 0 | C41: Product liability sits with Vitall for kits; add at supplement launch
A42: Misc / contingency | B42: 50 | C42: Returns, failed samples, postage
A43: FSA compliance (deferred) | B43: 0 | C43: Not needed until supplements ship
A44: ICO fee | B44: 3 | C44: £35/year
A46: TOTAL MONTHLY OVERHEAD | B46: =SUM(B35:B44) -> 88
A48: SUPPLEMENT CAPITAL (Self-Funded from Kit Revenue)
A49: Item | B49: Amount | C49: Notes
A50: OPTION A: Daily Stack Only (Phased)
A51: Daily Stack MOQ (500 units) | B51: 4000 | C51: First supplement to market
A52: Label + compliance (1 SKU) | B52: 1200 | C52: FSA-compliant, Ewa review
A53: Stability testing (1 SKU) | B53: 750 | C53: Required for FSA
A54: Total Option A | B54: =SUM(B51:B53) -> 5950
A56: OPTION B: Both SKUs (Full Launch)
A57: Daily Stack MOQ | B57: 4000
A58: Collagen MOQ (500 units) | B58: 1500
A59: Labels + compliance (2 SKUs) | B59: 2000
A60: Stability testing (2 SKUs) | B60: 1500
A61: Total Option B | B61: =SUM(B57:B60) -> 9000
A63: BREAKEVEN ANALYSIS
A64: Average kit gross margin (before processing) | B64: =(D6+D7+D8)/3 -> 59.166667
A65: Average kit retail price | B65: =(C6+C7+C8)/3 -> 132.33333
A66: Direct sale net margin (after Stripe) | B66: =B64-B65*B24 -> 55.858333
A67: Affiliate sale net margin (after Stripe + £15 fee) | B67: =B64-B65*B24-B25 -> 40.858333
A68: Blended net margin per kit (20% affiliate mix) | B68: =(1-B26)*B66+B26*B67 -> 52.858333 | C68: This is your key number — profit per kit after all variable costs
A70: KITS PER MONTH TO BREAK EVEN | B70: =ROUNDUP(B46/B68,0) -> 2 | C70: Monthly overhead ÷ blended margin per kit
A71: KITS PER WEEK TO BREAK EVEN | B71: =ROUNDUP(B70/4.33,0) -> 1
A73: Margin of safety at 17 kits/month (planning case M1) | B73: =17*B68-B46 -> 810.59167 | C73: Cash surplus above breakeven if Month 1 hits 17 kits
A75: Months to fund Daily Stack (Option A) | B75: =ROUNDUP(B54/(30*B68-B46),0) -> 4 | C75: At ~30 kits/month average (planning case avg)
A77: PER-KIT MARGIN DETAIL
B78: Kit 1 | C78: Kit 2 | D78: Kit 3
A79: Retail Price | B79: =C6 -> 99 | C79: =C7 -> 119 | D79: =C8 -> 179
A80: COGS | B80: =B6 -> 58.5 | C80: =B7 -> 63 | D80: =B8 -> 98
A81: Gross Margin | B81: =B79-B80 -> 40.5 | C81: =C79-C80 -> 56 | D81: =D79-D80 -> 81
A82: Gross Margin % | B82: =B81/B79 -> 0.40909091 | C82: =C81/C79 -> 0.47058824 | D82: =D81/D79 -> 0.45251397
A83: Stripe (2.5%) | B83: =B79*$B$24 -> 2.475 | C83: =C79*$B$24 -> 2.975 | D83: =D79*$B$24 -> 4.475
A84: Net Direct Margin | B84: =B81-B83 -> 38.025 | C84: =C81-C83 -> 53.025 | D84: =D81-D83 -> 76.525
A85: Net Direct % | B85: =B84/B79 -> 0.38409091 | C85: =C84/C79 -> 0.44558824 | D85: =D84/D79 -> 0.42751397
A87: Affiliate Fee (£15 flat) | B87: =$B$25 -> 15 | C87: =$B$25 -> 15 | D87: =$B$25 -> 15
A88: Net Affiliate Margin | B88: =B84-B87 -> 23.025 | C88: =C84-C87 -> 38.025 | D88: =D84-D87 -> 61.525
A89: Net Affiliate % | B89: =B88/B79 -> 0.23257576 | C89: =C88/C79 -> 0.31953782 | D89: =D88/D79 -> 0.34371508
A91: Blended Margin (20% aff) | B91: =(1-$B$26)*B84+$B$26*B88 -> 35.025 | C91: =(1-$B$26)*C84+$B$26*C88 -> 50.025 | D91: =(1-$B$26)*D84+$B$26*D88 -> 73.525
A92: Blended % | B92: =B91/B79 -> 0.35378788 | C92: =C91/C79 -> 0.42037815 | D92: =D91/D79 -> 0.41075419

Sheet 6-Month P&L
A1: PHASE 0 — 6-MONTH P&L
A2: Organic-First | Premium Pricing | Cash-Positive from Month 1
B4: Month 1 | C4: Month 2 | D4: Month 3 | E4: Month 4 | F4: Month 5 | G4: Month 6 | H4: 6-Mo Total
A5: KIT SALES VOLUME
A6: Kit 1 — Hormone Check | B6: 5 | C6: 8 | D6: 10 | E6: 14 | F6: 16 | G6: 20 | H6: =SUM(B6:G6) -> 73
A7: Kit 2 — Energy & Metabolism | B7: 10 | C7: 14 | D7: 20 | E7: 26 | F7: 30 | G7: 36 | H7: =SUM(B7:G7) -> 136
A8: Kit 3 — Combo Test | B8: 2 | C8: 4 | D8: 6 | E8: 8 | F8: 10 | G8: 12 | H8: =SUM(B8:G8) -> 42
A9: Total Kits Sold | B9: =B6+B7+B8 -> 17 | C9: =C6+C7+C8 -> 26 | D9: =D6+D7+D8 -> 36 | E9: =E6+E7+E8 -> 48 | F9: =F6+F7+F8 -> 56 | G9: =G6+G7+G8 -> 68 | H9: =H6+H7+H8 -> 251
A10: Cumulative Kits | B10: =B9 -> 17 | C10: =B10+C9 -> 43 | D10: =C10+D9 -> 79 | E10: =D10+E9 -> 127 | F10: =E10+F9 -> 183 | G10: =F10+G9 -> 251 | H10: =G10 -> 251
A12: KIT REVENUE
A13: Kit 1 — Hormone Check | B13: =B6*Assumptions!C6 -> 495 | C13: =C6*Assumptions!C6 -> 792 | D13: =D6*Assumptions!C6 -> 990 | E13: =E6*Assumptions!C6 -> 1386 | F13: =F6*Assumptions!C6 -> 1584 | G13: =G6*Assumptions!C6 -> 1980 | H13: =SUM(B13:G13) -> 7227
A14: Kit 2 — Energy & Metabolism | B14: =B7*Assumptions!C7 -> 1190 | C14: =C7*Assumptions!C7 -> 1666 | D14: =D7*Assumptions!C7 -> 2380 | E14: =E7*Assumptions!C7 -> 3094 | F14: =F7*Assumptions!C7 -> 3570 | G14: =G7*Assumptions!C7 -> 4284 | H14: =SUM(B14:G14) -> 16184
A15: Kit 3 — Combo Test | B15: =B8*Assumptions!C8 -> 358 | C15: =C8*Assumptions!C8 -> 716 | D15: =D8*Assumptions!C8 -> 1074 | E15: =E8*Assumptions!C8 -> 1432 | F15: =F8*Assumptions!C8 -> 1790 | G15: =G8*Assumptions!C8 -> 2148 | H15: =SUM(B15:G15) -> 7518
A16: Total Kit Revenue | B16: =B13+B14+B15 -> 2043 | C16: =C13+C14+C15 -> 3174 | D16: =D13+D14+D15 -> 4444 | E16: =E13+E14+E15 -> 5912 | F16: =F13+F14+F15 -> 6944 | G16: =G13+G14+G15 -> 8412 | H16: =H13+H14+H15 -> 30929
A18: KIT COGS
A19: Kit 1 — Hormone Check COGS | B19: =B6*Assumptions!B6 -> 292.5 | C19: =C6*Assumptions!B6 -> 468 | D19: =D6*Assumptions!B6 -> 585 | E19: =E6*Assumptions!B6 -> 819 | F19: =F6*Assumptions!B6 -> 936 | G19: =G6*Assumptions!B6 -> 1170 | H19: =SUM(B19:G19) -> 4270.5
A20: Kit 2 — Energy & Metabolism COGS | B20: =B7*Assumptions!B7 -> 630 | C20: =C7*Assumptions!B7 -> 882 | D20: =D7*Assumptions!B7 -> 1260 | E20: =E7*Assumptions!B7 -> 1638 | F20: =F7*Assumptions!B7 -> 1890 | G20: =G7*Assumptions!B7 -> 2268 | H20: =SUM(B20:G20) -> 8568
A21: Kit 3 — Combo Test COGS | B21: =B8*Assumptions!B8 -> 196 | C21: =C8*Assumptions!B8 -> 392 | D21: =D8*Assumptions!B8 -> 588 | E21: =E8*Assumptions!B8 -> 784 | F21: =F8*Assumptions!B8 -> 980 | G21: =G8*Assumptions!B8 -> 1176 | H21: =SUM(B21:G21) -> 4116
A22: Total Kit COGS | B22: =B19+B20+B21 -> 1118.5 | C22: =C19+C20+C21 -> 1742 | D22: =D19+D20+D21 -> 2433 | E22: =E19+E20+E21 -> 3241 | F22: =F19+F20+F21 -> 3806 | G22: =G19+G20+G21 -> 4614 | H22: =H19+H20+H21 -> 16954.5
A24: Kit Gross Profit | B24: =B16-B22 -> 924.5 | C24: =C16-C22 -> 1432 | D24: =D16-D22 -> 2011 | E24: =E16-E22 -> 2671 | F24: =F16-F22 -> 3138 | G24: =G16-G22 -> 3798 | H24: =H16-H22 -> 13974.5
A25: Kit Gross Margin % | B25: =IF(B16=0,0,B24/B16) -> 0.4525208 | C25: =IF(C16=0,0,C24/C16) -> 0.45116572 | D25: =IF(D16=0,0,D24/D16) -> 0.45252025 | E25: =IF(E16=0,0,E24/E16) -> 0.45179296 | F25: =IF(F16=0,0,F24/F16) -> 0.45190092 | G25: =IF(G16=0,0,G24/G16) -> 0.45149786 | H25: =IF(H16=0,0,H24/H16) -> 0.45182515
A27: SUPPLEMENT SUBSCRIBERS
A28: New subs (12% of Kit 2+3 buyers) | B28: =ROUND((B7+B8)*Assumptions!B27,0) -> 1 | C28: =ROUND((C7+C8)*Assumptions!B27,0) -> 2 | D28: =ROUND((D7+D8)*Assumptions!B27,0) -> 3 | E28: =ROUND((E7+E8)*Assumptions!B27,0) -> 4 | F28: =ROUND((F7+F8)*Assumptions!B27,0) -> 5 | G28: =ROUND((G7+G8)*Assumptions!B27,0) -> 6 | H28: =SUM(B28:G28) -> 21
A29: Churned | B29: 0 | C29: =ROUND(B30*Assumptions!B28,0) -> 0 | D29: =ROUND(C30*Assumptions!B28,0) -> 0 | E29: =ROUND(D30*Assumptions!B28,0) -> 0 | F29: =ROUND(E30*Assumptions!B28,0) -> 0 | G29: =ROUND(F30*Assumptions!B28,0) -> 0 | H29: =SUM(B29:G29) -> 0
A30: Active Subscribers (EOM) | B30: =B28-B29 -> 1 | C30: =B30+C28-C29 -> 3 | D30: =C30+D28-D29 -> 6 | E30: =D30+E28-E29 -> 10 | F30: =E30+F28-F29 -> 15 | G30: =F30+G28-G29 -> 21 | H30: =G30 -> 21
A32: SUPPLEMENT FINANCIALS
A33: Supplement Revenue | B33: =B30*Assumptions!C18 -> 34.95 | C33: =C30*Assumptions!C18 -> 104.85 | D33: =D30*Assumptions!C18 -> 209.7 | E33: =E30*Assumptions!C18 -> 349.5 | F33: =F30*Assumptions!C18 -> 524.25 | G33: =G30*Assumptions!C18 -> 733.95 | H33: =SUM(B33:G33) -> 1957.2
A34: Supplement COGS | B34: =B30*Assumptions!B18 -> 15 | C34: =C30*Assumptions!B18 -> 45 | D34: =D30*Assumptions!B18 -> 90 | E34: =E30*Assumptions!B18 -> 150 | F34: =F30*Assumptions!B18 -> 225 | G34: =G30*Assumptions!B18 -> 315 | H34: =SUM(B34:G34) -> 840
A35: Supplement Gross Profit | B35: =B33-B34 -> 19.95 | C35: =C33-C34 -> 59.85 | D35: =D33-D34 -> 119.7 | E35: =E33-E34 -> 199.5 | F35: =F33-F34 -> 299.25 | G35: =G33-G34 -> 418.95 | H35: =H33-H34 -> 1117.2
A37: FOUNDING MEMBER DEPOSITS
A38: T-kits sold (Kit 1 + Kit 3) | B38: =B6+B8 -> 7 | C38: =C6+C8 -> 12 | D38: =D6+D8 -> 16 | E38: =E6+E8 -> 22 | F38: =F6+F8 -> 26 | G38: =G6+G8 -> 32 | H38: =SUM(B38:G38) -> 115
A39: Low-T results (35%) | B39: =ROUND(B38*Assumptions!B30,0) -> 2 | C39: =ROUND(C38*Assumptions!B30,0) -> 4 | D39: =ROUND(D38*Assumptions!B30,0) -> 6 | E39: =ROUND(E38*Assumptions!B30,0) -> 8 | F39: =ROUND(F38*Assumptions!B30,0) -> 9 | G39: =ROUND(G38*Assumptions!B30,0) -> 11 | H39: =SUM(B39:G39) -> 40
A40: Deposits secured (50%) | B40: =ROUND(B39*Assumptions!B31,0) -> 1 | C40: =ROUND(C39*Assumptions!B31,0) -> 2 | D40: =ROUND(D39*Assumptions!B31,0) -> 3 | E40: =ROUND(E39*Assumptions!B31,0) -> 4 | F40: =ROUND(F39*Assumptions!B31,0) -> 5 | G40: =ROUND(G39*Assumptions!B31,0) -> 6 | H40: =SUM(B40:G40) -> 21
A41: Deposit Revenue | B41: =B40*Assumptions!B29 -> 75 | C41: =C40*Assumptions!B29 -> 150 | D41: =D40*Assumptions!B29 -> 225 | E41: =E40*Assumptions!B29 -> 300 | F41: =F40*Assumptions!B29 -> 375 | G41: =G40*Assumptions!B29 -> 450 | H41: =SUM(B41:G41) -> 1575
A43: REVENUE SUMMARY
A44: Kit Revenue | B44: =B16 -> 2043 | C44: =C16 -> 3174 | D44: =D16 -> 4444 | E44: =E16 -> 5912 | F44: =F16 -> 6944 | G44: =G16 -> 8412 | H44: =H16 -> 30929
A45: Supplement Revenue | B45: =B33 -> 34.95 | C45: =C33 -> 104.85 | D45: =D33 -> 209.7 | E45: =E33 -> 349.5 | F45: =F33 -> 524.25 | G45: =G33 -> 733.95 | H45: =H33 -> 1957.2
A46: Deposit Revenue | B46: =B41 -> 75 | C46: =C41 -> 150 | D46: =D41 -> 225 | E46: =E41 -> 300 | F46: =F41 -> 375 | G46: =G41 -> 450 | H46: =H41 -> 1575
A47: TOTAL REVENUE | B47: =B44+B45+B46 -> 2152.95 | C47: =C44+C45+C46 -> 3428.85 | D47: =D44+D45+D46 -> 4878.7 | E47: =E44+E45+E46 -> 6561.5 | F47: =F44+F45+F46 -> 7843.25 | G47: =G44+G45+G46 -> 9595.95 | H47: =H44+H45+H46 -> 34461.2
A49: TOTAL COGS
A50: Kit COGS | B50: =B22 -> 1118.5 | C50: =C22 -> 1742 | D50: =D22 -> 2433 | E50: =E22 -> 3241 | F50: =F22 -> 3806 | G50: =G22 -> 4614 | H50: =H22 -> 16954.5
A51: Supplement COGS | B51: =B34 -> 15 | C51: =C34 -> 45 | D51: =D34 -> 90 | E51: =E34 -> 150 | F51: =F34 -> 225 | G51: =G34 -> 315 | H51: =H34 -> 840
A52: TOTAL COGS | B52: =B50+B51 -> 1133.5 | C52: =C50+C51 -> 1787 | D52: =D50+D51 -> 2523 | E52: =E50+E51 -> 3391 | F52: =F50+F51 -> 4031 | G52: =G50+G51 -> 4929 | H52: =H50+H51 -> 17794.5
A54: GROSS PROFIT | B54: =B47-B52 -> 1019.45 | C54: =C47-C52 -> 1641.85 | D54: =D47-D52 -> 2355.7 | E54: =E47-E52 -> 3170.5 | F54: =F47-F52 -> 3812.25 | G54: =G47-G52 -> 4666.95 | H54: =H47-H52 -> 16666.7
A55: Gross Margin % | B55: =IF(B47=0,0,B54/B47) -> 0.47351309 | C55: =IF(C47=0,0,C54/C47) -> 0.47883401 | D55: =IF(D47=0,0,D54/D47) -> 0.48285404 | E55: =IF(E47=0,0,E54/E47) -> 0.48319744 | F55: =IF(F47=0,0,F54/F47) -> 0.48605489 | G55: =IF(G47=0,0,G54/G47) -> 0.4863458 | H55: =IF(H47=0,0,H54/H47) -> 0.48363667
A57: OPERATING EXPENSES
A58: Fixed Overhead | B58: =Assumptions!B46 -> 88 | C58: =Assumptions!B46 -> 88 | D58: =Assumptions!B46 -> 88 | E58: =Assumptions!B46 -> 88 | F58: =Assumptions!B46 -> 88 | G58: =Assumptions!B46 -> 88 | H58: =SUM(B58:G58) -> 528
A59: Payment Processing (Stripe 2.5%) | B59: =B47*Assumptions!B24 -> 53.82375 | C59: =C47*Assumptions!B24 -> 85.72125 | D59: =D47*Assumptions!B24 -> 121.9675 | E59: =E47*Assumptions!B24 -> 164.0375 | F59: =F47*Assumptions!B24 -> 196.08125 | G59: =G47*Assumptions!B24 -> 239.89875 | H59: =SUM(B59:G59) -> 861.53
A60: Affiliate Fees (£15 × affiliate kit sales) | B60: =B9*Assumptions!B26*Assumptions!B25 -> 51 | C60: =C9*Assumptions!B26*Assumptions!B25 -> 78 | D60: =D9*Assumptions!B26*Assumptions!B25 -> 108 | E60: =E9*Assumptions!B26*Assumptions!B25 -> 144 | F60: =F9*Assumptions!B26*Assumptions!B25 -> 168 | G60: =G9*Assumptions!B26*Assumptions!B25 -> 204 | H60: =SUM(B60:G60) -> 753
A61: TOTAL OPEX | B61: =B58+B59+B60 -> 192.82375 | C61: =C58+C59+C60 -> 251.72125 | D61: =D58+D59+D60 -> 317.9675 | E61: =E58+E59+E60 -> 396.0375 | F61: =F58+F59+F60 -> 452.08125 | G61: =G58+G59+G60 -> 531.89875 | H61: =H58+H59+H60 -> 2142.53
A63: NET MONTHLY CONTRIBUTION | B63: =B54-B61 -> 826.62625 | C63: =C54-C61 -> 1390.1288 | D63: =D54-D61 -> 2037.7325 | E63: =E54-E61 -> 2774.4625 | F63: =F54-F61 -> 3360.1687 | G63: =G54-G61 -> 4135.0513 | H63: =H54-H61 -> 14524.17
A64: Net Margin % | B64: =IF(B47=0,0,B63/B47) -> 0.38395051 | C64: =IF(C47=0,0,C63/C47) -> 0.40542128 | D64: =IF(D47=0,0,D63/D47) -> 0.4176794 | E64: =IF(E47=0,0,E63/E47) -> 0.42283967 | F64: =IF(F47=0,0,F63/F47) -> 0.42841536 | G64: =IF(G47=0,0,G63/G47) -> 0.4309163 | H64: =IF(H47=0,0,H63/H47) -> 0.42146443
A66: CUMULATIVE CASH
A67: Cumulative Cash Position | B67: =B63 -> 826.62625 | C67: =B67+C63 -> 2216.755 | D67: =C67+D63 -> 4254.4875 | E67: =D67+E63 -> 7028.95 | F67: =E67+F63 -> 10389.119 | G67: =F67+G63 -> 14524.17 | H67: =G67 -> 14524.17
A69: KEY METRICS
A70: Blended Revenue per Kit | B70: =IF(B9=0,0,B16/B9) -> 120.17647 | C70: =IF(C9=0,0,C16/C9) -> 122.07692 | D70: =IF(D9=0,0,D16/D9) -> 123.44444 | E70: =IF(E9=0,0,E16/E9) -> 123.16667 | F70: =IF(F9=0,0,F16/F9) -> 124 | G70: =IF(G9=0,0,G16/G9) -> 123.70588 | H70: =IF(H9=0,0,H16/H9) -> 123.22311
A71: Supplement MRR (EOM) | B71: =B30*Assumptions!C18 -> 34.95 | C71: =C30*Assumptions!C18 -> 104.85 | D71: =D30*Assumptions!C18 -> 209.7 | E71: =E30*Assumptions!C18 -> 349.5 | F71: =F30*Assumptions!C18 -> 524.25 | G71: =G30*Assumptions!C18 -> 733.95 | H71: =G71 -> 733.95
A72: Founding Member Deposits (cum.) | B72: =B40 -> 1 | C72: =B72+C40 -> 3 | D72: =C72+D40 -> 6 | E72: =D72+E40 -> 10 | F72: =E72+F40 -> 15 | G72: =F72+G40 -> 21 | H72: =G72 -> 21
A73: Margin of Safety (Net - Breakeven) | B73: =B63 -> 826.62625 | C73: =C63 -> 1390.1288 | D73: =D63 -> 2037.7325 | E73: =E63 -> 2774.4625 | F73: =F63 -> 3360.1687 | G73: =G63 -> 4135.0513 | H73: =SUM(B73:G73) -> 14524.17
